{"version": 0.6, "generator": "Overpass API 0.7.61.5 4133829e", "osm3s": {"timestamp_osm_base": "2024-03-06T10:41:59Z", "copyright": "The data included in this document is from www.openstreetmap.org. The data is made available under ODbL."}, "elements": [{"type": "node", "id": 7051660809, "lat": 32.823323, "lon": 45.0442028}, {"type": "node", "id": 7051660810, "lat": 32.8231855, "lon": 45.0443798}, {"type": "node", "id": 7051660811, "lat": 32.823287, "lon": 45.0445998}, {"type": "node", "id": 7051660812, "lat": 32.8234865, "lon": 45.0443624}, {"type": "way", "id": 754865149, "nodes": [7051660812, 7051660811, 7051660810, 7051660809, 7051660812], "tags": {"waterway": "dam"}}]}