{"version": 0.6, "generator": "Overpass API 0.7.61.5 4133829e", "osm3s": {"timestamp_osm_base": "2024-03-06T11:08:30Z", "copyright": "The data included in this document is from www.openstreetmap.org. The data is made available under ODbL."}, "elements": [{"type": "node", "id": 3646034833, "lat": -1.0898536, "lon": 35.8702876, "tags": {"addr:street": "Kaplong-Narok-Maai Road", "amenity": "college", "name": "Rocky Driving School"}}, {"type": "node", "id": 6054892195, "lat": -1.1228336, "lon": 35.9914508}, {"type": "node", "id": 6054892196, "lat": -1.1230204, "lon": 35.9918881}, {"type": "node", "id": 6054892197, "lat": -1.1235884, "lon": 35.9919254}, {"type": "node", "id": 6054892198, "lat": -1.1236828, "lon": 35.9909862}, {"type": "node", "id": 6054892199, "lat": -1.1229158, "lon": 35.9910097}, {"type": "node", "id": 6263872675, "lat": -1.1232869, "lon": 35.9919835}, {"type": "node", "id": 6263872994, "lat": -1.1234322, "lon": 35.9908058}, {"type": "node", "id": 6263873014, "lat": -1.1237574, "lon": 35.9913545}, {"type": "way", "id": 643401187, "nodes": [6054892195, 6054892196, 6263872675, 6054892197, 6263873014, 6054892198, 6263872994, 6054892199, 6054892195], "tags": {"addr:city": "Narok", "addr:street": "Kaplong-Narok-Maai Road", "amenity": "college", "name": "Maasai Mara Technical College"}}]}