{"version": 0.6, "generator": "Overpass API 0.7.61.5 4133829e", "osm3s": {"timestamp_osm_base": "2024-03-05T11:24:46Z", "copyright": "The data included in this document is from www.openstreetmap.org. The data is made available under ODbL."}, "elements": [{"type": "node", "id": 1820144645, "lat": 4.9607455, "lon": -2.4535657, "tags": {"name": "Sanzule", "place": "village"}}, {"type": "node", "id": 1820144651, "lat": 4.9626628, "lon": -2.463654, "tags": {"name": "Krisan", "place": "village"}}, {"type": "node", "id": 1820144652, "lat": 4.964505, "lon": -2.472958, "tags": {"name": "Eikwe", "place": "village", "wikidata": "Q5349276"}}, {"type": "node", "id": 1820144653, "lat": 4.9661211, "lon": -2.4825469, "tags": {"name": "Ngalekpole", "place": "village"}}, {"type": "node", "id": 1820144655, "lat": 4.9685872, "lon": -2.4946679, "tags": {"name": "Ngalekyi", "place": "village"}}, {"type": "node", "id": 1820144658, "lat": 4.9701789, "lon": -2.5014593, "tags": {"name": "Beku", "place": "village"}}, {"type": "node", "id": 1820144662, "lat": 4.9736328, "lon": -2.5220397, "tags": {"name": "Anokyi", "place": "village"}}, {"type": "node", "id": 1820144676, "lat": 4.9764674, "lon": -2.4551181, "tags": {"place": "village"}}, {"type": "node", "id": 1820144680, "lat": 4.9804404, "lon": -2.5547548, "tags": {"name": "Atuabo", "place": "village", "wikidata": "Q20537713"}}, {"type": "node", "id": 2145887477, "lat": 4.9577273, "lon": -2.4453273, "tags": {"name": "Dogbeyvi Kordzi", "place": "village"}}]}