{"version": 0.6, "generator": "Overpass API 0.7.61.5 4133829e", "osm3s": {"timestamp_osm_base": "2024-03-06T11:49:22Z", "copyright": "The data included in this document is from www.openstreetmap.org. The data is made available under ODbL."}, "elements": [{"type": "node", "id": 6384431934, "lat": -3.1829629, "lon": 37.6291773}, {"type": "node", "id": 6384431935, "lat": -3.1831641, "lon": 37.6292054}, {"type": "node", "id": 6384431936, "lat": -3.1831313, "lon": 37.6293717}, {"type": "node", "id": 6384431937, "lat": -3.1829161, "lon": 37.6293155}, {"type": "way", "id": 681746107, "nodes": [6384431934, 6384431935, 6384431936, 6384431937, 6384431934], "tags": {"natural": "water", "water": "reservoir"}}]}