{"version": 0.6, "generator": "Overpass API 0.7.61.5 4133829e", "osm3s": {"timestamp_osm_base": "2024-03-06T11:22:45Z", "copyright": "The data included in this document is from www.openstreetmap.org. The data is made available under ODbL."}, "elements": [{"type": "node", "id": 3954839500, "lat": 1.2317238, "lon": 34.2468473, "tags": {"addr:city": "Sironko Town Council", "addr:street": "Sironko Kapchorwa", "amenity": "bank", "name": "Sironko", "opening_hours": "Mo-Fr 09:00-17:00", "operator": "Stanbic Bank Uganda"}}]}