{"version": 0.6, "generator": "Overpass API 0.7.61.5 4133829e", "osm3s": {"timestamp_osm_base": "2024-03-05T14:50:30Z", "copyright": "The data included in this document is from www.openstreetmap.org. The data is made available under ODbL."}, "elements": [{"type": "node", "id": 285158305, "lat": 56.5173322, "lon": 13.3169705, "tags": {"amenity": "bank", "atm": "yes", "name": "Laholms Sparbank"}}, {"type": "node", "id": 773525176, "lat": 56.8332085, "lon": 13.9396997, "tags": {"amenity": "bank", "brand": "SEB", "brand:wikidata": "Q975655", "brand:wikipedia": "sv:Skandinaviska Enskilda Banken", "name": "SEB", "opening_hours": "Mo-Fr 10:00-13:00", "wheelchair": "yes"}}, {"type": "node", "id": 773525490, "lat": 56.8336116, "lon": 13.9413797, "tags": {"amenity": "bank", "brand": "Handelsbanken", "brand:wikidata": "Q1421630", "brand:wikipedia": "sv:Handelsbanken", "name": "Handelsbanken", "opening_hours": "Mo-We,Fr 10:00-14:00; Th 10:00-17:30", "wheelchair": "yes"}}, {"type": "node", "id": 1862790091, "lat": 56.4615327, "lon": 13.5954725, "tags": {"amenity": "bank", "atm": "yes", "check_date": "2022-10-08", "name": "Markaryds Sparbank"}}, {"type": "node", "id": 4173370131, "lat": 56.8337282, "lon": 13.9371124}, {"type": "node", "id": 4173370133, "lat": 56.8335734, "lon": 13.936995}, {"type": "node", "id": 4173370135, "lat": 56.8335362, "lon": 13.9371589}, {"type": "node", "id": 4173370136, "lat": 56.8335882, "lon": 13.9369296}, {"type": "node", "id": 4173370137, "lat": 56.8332791, "lon": 13.9369639}, {"type": "node", "id": 4173370138, "lat": 56.8333311, "lon": 13.9367347}, {"type": "node", "id": 4225656775, "lat": 56.8336415, "lon": 13.9374941}, {"type": "node", "id": 4927485398, "lat": 56.5478415, "lon": 13.9542426, "tags": {"amenity": "bank", "name": "Sparbanken Eken"}}, {"type": "node", "id": 5111031932, "lat": 56.5499785, "lon": 13.7316979, "tags": {"amenity": "bank", "atm": "yes", "brand": "Swedbank", "brand:wikidata": "Q1145493", "brand:wikipedia": "sv:Swedbank", "name": "Swedbank"}}, {"type": "node", "id": 5703243036, "lat": 56.8326492, "lon": 13.9336316}, {"type": "node", "id": 5782998842, "lat": 56.5174691, "lon": 13.3168163}, {"type": "node", "id": 5782998843, "lat": 56.517352, "lon": 13.3168145}, {"type": "node", "id": 5782998844, "lat": 56.5173559, "lon": 13.3171268}, {"type": "node", "id": 5782998845, "lat": 56.5174715, "lon": 13.3171322}, {"type": "node", "id": 6433811028, "lat": 56.8334868, "lon": 13.9373768}, {"type": "node", "id": 6433811029, "lat": 56.8335604, "lon": 13.9374326}, {"type": "node", "id": 6551056276, "lat": 56.8336849, "lon": 13.9373033, "tags": {"entrance": "main"}}, {"type": "node", "id": 6551056277, "lat": 56.8336015, "lon": 13.9370163}, {"type": "node", "id": 9376740891, "lat": 56.8320214, "lon": 13.9333145}, {"type": "node", "id": 9376740894, "lat": 56.8325056, "lon": 13.9328073}, {"type": "node", "id": 9376740895, "lat": 56.8321179, "lon": 13.9329335}, {"type": "node", "id": 9376740896, "lat": 56.8322017, "lon": 13.9330755}, {"type": "node", "id": 9376740897, "lat": 56.8321252, "lon": 13.932953}, {"type": "node", "id": 9376740899, "lat": 56.8321154, "lon": 13.9329812}, {"type": "node", "id": 9376740901, "lat": 56.8320788, "lon": 13.9329883}, {"type": "node", "id": 9376740902, "lat": 56.8320053, "lon": 13.9332024}, {"type": "node", "id": 9376740904, "lat": 56.8321892, "lon": 13.9329979}, {"type": "node", "id": 9376740906, "lat": 56.832219, "lon": 13.9329708}, {"type": "node", "id": 9376740907, "lat": 56.8320837, "lon": 13.9331442}, {"type": "node", "id": 9376740908, "lat": 56.8320866, "lon": 13.933022}, {"type": "node", "id": 9376740909, "lat": 56.8321529, "lon": 13.9329361}, {"type": "node", "id": 9376740910, "lat": 56.8325406, "lon": 13.9340654}, {"type": "node", "id": 9376740911, "lat": 56.8327859, "lon": 13.9331397}, {"type": "node", "id": 9376740912, "lat": 56.8320943, "lon": 13.9330821}, {"type": "node", "id": 9376740914, "lat": 56.8321135, "lon": 13.9329733}, {"type": "node", "id": 9376740916, "lat": 56.8322244, "lon": 13.9333639}, {"type": "node", "id": 9376768417, "lat": 56.8322425, "lon": 13.9330488}, {"type": "node", "id": 9376768418, "lat": 56.8321982, "lon": 13.9328786}, {"type": "node", "id": 9379626161, "lat": 56.8320217, "lon": 13.9331734}, {"type": "node", "id": 9379626162, "lat": 56.8321221, "lon": 13.9332714}, {"type": "node", "id": 9379626165, "lat": 56.8320418, "lon": 13.9333054}, {"type": "node", "id": 9379626166, "lat": 56.8320095, "lon": 13.9332311, "tags": {"access": "customers", "door": "sliding", "entrance": "yes", "level": "0"}}, {"type": "node", "id": 9379626168, "lat": 56.8320177, "lon": 13.9332873, "tags": {"access": "customers", "door": "sliding", "entrance": "yes", "level": "0"}}, {"type": "node", "id": 9380232628, "lat": 56.832033, "lon": 13.9331681}, {"type": "node", "id": 9381351503, "lat": 56.8326087, "lon": 13.9329346}, {"type": "node", "id": 9381351504, "lat": 56.8326246, "lon": 13.9328857}, {"type": "node", "id": 9381351505, "lat": 56.8325586, "lon": 13.9328725}, {"type": "node", "id": 9381351506, "lat": 56.8325761, "lon": 13.9328265}, {"type": "node", "id": 9381353936, "lat": 56.8322747, "lon": 13.9329493}, {"type": "node", "id": 9381353937, "lat": 56.8322893, "lon": 13.933017}, {"type": "way", "id": 416586459, "nodes": [4173370131, 6551056276, 4225656775, 6433811029, 6433811028, 4173370135, 4173370137, 4173370138, 4173370136, 4173370133, 6551056277, 4173370131], "tags": {"amenity": "bank", "atm": "yes", "brand": "Swedbank", "brand:wikidata": "Q1145493", "brand:wikipedia": "sv:Swedbank", "building": "yes", "drive_through": "no", "name": "Swedbank"}}, {"type": "way", "id": 610645607, "nodes": [5782998842, 5782998843, 5782998844, 5782998845, 5782998842], "tags": {"amenity": "bank", "atm": "yes", "building": "yes"}}, {"type": "way", "id": 1016614620, "nodes": [9376740916, 9379626162, 9379626165, 9376740891, 9379626168, 9379626166, 9376740902, 9379626161, 9380232628, 9376740907, 9376740912, 9376740908, 9376740901, 9376740895, 9376740897, 9376740914, 9376740899, 9376740909, 9376768418, 9376740906, 9376740904, 9376740896, 9376768417, 9381353937, 9381353936, 9376740894, 9381351505, 9381351506, 9381351504, 9381351503, 9376740911, 5703243036, 9376740910, 9376740916], "tags": {"addr:city": "Ljungby", "addr:country": "SE", "addr:housenumber": "2", "addr:street": "Stationsgatan", "atm": "yes", "brand": "Willys", "brand:wikidata": "Q10720214", "brand:wikipedia": "sv:Willys", "check_date:opening_hours": "2023-05-19", "currency:SEK": "yes", "currency:others": "no", "delivery": "yes", "drive_through": "no", "fair_trade": "yes", "indoor": "room", "internet_access": "wlan", "internet_access:fee": "no", "level": "0", "name": "Willys", "opening_hours": "Mo-Sa 08:00-21:00; Su 09:00-21:00", "operator": "AxFood", "organic": "yes", "payment:coins": "yes", "payment:mastercard": "yes", "payment:notes": "yes", "payment:samsung_pay": "yes", "payment:visa": "yes", "room": "shop", "shop": "supermarket", "wheelchair": "yes"}}]}