{"version": 0.6, "generator": "Overpass API 0.7.61.5 4133829e", "osm3s": {"timestamp_osm_base": "2024-03-06T11:09:29Z", "copyright": "The data included in this document is from www.openstreetmap.org. The data is made available under ODbL."}, "elements": [{"type": "node", "id": 4070602472, "lat": 35.9459302, "lon": 42.5725382}, {"type": "node", "id": 4070602473, "lat": 35.9456674, "lon": 42.5727715}, {"type": "node", "id": 4070602474, "lat": 35.9454025, "lon": 42.5722995}, {"type": "node", "id": 4070602475, "lat": 35.9456794, "lon": 42.5720621}, {"type": "way", "id": 404803462, "nodes": [4070602472, 4070602473, 4070602474, 4070602475, 4070602472], "tags": {"amenity": "hospital", "emergency": "yes", "healthcare": "hospital", "name": "\u0645\u0631\u0643\u0632 \u0635\u062d\u064a \u062a\u0644 \u0639\u0628\u0637\u0629", "name:ar": "\u0645\u0631\u0643\u0632 \u0635\u062d\u064a \u062a\u0644 \u0639\u0628\u0637\u0629", "name:en": "Tall Abtah Health Centre"}}]}