{"version": 0.6, "generator": "Overpass API 0.7.61.5 4133829e", "osm3s": {"timestamp_osm_base": "2024-03-05T14:47:30Z", "copyright": "The data included in this document is from www.openstreetmap.org. The data is made available under ODbL."}, "elements": [{"type": "node", "id": 616765356, "lat": 58.4275716, "lon": 15.5826993, "tags": {"amenity": "atm"}}, {"type": "node", "id": 658855470, "lat": 58.4480477, "lon": 14.8897438, "tags": {"amenity": "atm", "check_date": "2021-06-23", "email": "hk@vadstenasparbank.se", "fax": "+46 14313647", "name": "Vadstena Sparbank", "opening_hours": "Mo-We,Fr 10:00-15:00; Th 10:00-17:30", "phone": "+46 14375500", "website": "https://www.vadstenasparbank.se/"}}, {"type": "node", "id": 738673236, "lat": 58.3883475, "lon": 15.5651016, "tags": {"amenity": "atm", "check_date": "2021-02-13", "currency:SEK": "yes"}}, {"type": "node", "id": 1714394909, "lat": 58.5365511, "lon": 15.0400522, "tags": {"amenity": "atm"}}, {"type": "node", "id": 1714394921, "lat": 58.5361847, "lon": 15.0382539, "tags": {"amenity": "atm"}}, {"type": "node", "id": 1731868391, "lat": 58.5408823, "lon": 15.0686069, "tags": {"amenity": "atm"}}, {"type": "node", "id": 1734172569, "lat": 58.5361257, "lon": 15.0370528, "tags": {"amenity": "atm"}}, {"type": "node", "id": 1863121712, "lat": 58.3229014, "lon": 15.1324996, "tags": {"amenity": "atm", "operator": "Nordea"}}, {"type": "node", "id": 1863132804, "lat": 58.3257182, "lon": 15.1294082, "tags": {"amenity": "atm"}}, {"type": "node", "id": 1863132806, "lat": 58.3256013, "lon": 15.1249879, "tags": {"amenity": "atm", "brand": "Bankomat", "brand:wikipedia": "sv:Bankomat", "operator": "Bankomat AB"}}, {"type": "node", "id": 4075443810, "lat": 58.4007629, "lon": 15.5780023, "tags": {"amenity": "atm", "brand": "Bankomat", "operator": "Bankomat AB"}}, {"type": "node", "id": 4158417269, "lat": 58.4089464, "lon": 15.5630006, "tags": {"amenity": "atm", "opening_hours": "24/7", "operator": "Bankomat AB", "wheelchair": "yes"}}, {"type": "node", "id": 4881547324, "lat": 58.43192, "lon": 15.5916989, "tags": {"amenity": "atm", "brand": "Icabanken", "check_date": "2021-04-12", "opening_hours": "24/7", "operator": "ICA Banken"}}, {"type": "node", "id": 5004362654, "lat": 58.5625794, "lon": 15.2815448, "tags": {"amenity": "atm"}}, {"type": "node", "id": 7923563065, "lat": 58.3661296, "lon": 15.2944466, "tags": {"amenity": "atm", "brand": "Bankomat", "operator": "Bankomat AB"}}, {"type": "node", "id": 9535205935, "lat": 58.4332364, "lon": 15.5857268, "tags": {"amenity": "atm", "brand": "Bankomat", "level": "0"}}]}